Metadata-Version: 2.1
Name: unichain-py-test
Version: 0.1.0
Summary: Sample unichain-py-test by Python
Home-page: https://github.com/kennethreitz/unichainpy
Author: Real Elon Musk
Author-email: realelonmusk102@gmail.com
License: Copyright (c) 2017, Kenneth Reitz
Platform: UNKNOWN
License-File: LICENSE
